tf_core/__init__.py
tf_core/annotation.py
tf_core/bow_dataset.py
tf_core/bow_model_contructor.py
tf_core/document.py
tf_core/document_corpus.py
tf_core/helpers.py
tf_core/textflows.py
tf_core/nltoolkit/__init__.py
tf_core/nltoolkit/helpers.py
tf_core/nltoolkit/interaction_views.py
tf_core/nltoolkit/library.py
tf_core/nltoolkit/random_colors.py
tf_core/nltoolkit/urls.py
tf_core/nltoolkit/views.py
tf_core/nltoolkit/visualization_views.py
tf_core/nltoolkit/lib/__init__.py
tf_core/nltoolkit/lib/bag_of_words.py
tf_core/nltoolkit/lib/chunking.py
tf_core/nltoolkit/lib/classification.py
tf_core/nltoolkit/lib/clustering.py
tf_core/nltoolkit/lib/document_converters.py
tf_core/nltoolkit/lib/document_corpus.py
tf_core/nltoolkit/lib/named_entity_extraction.py
tf_core/nltoolkit/lib/part_of_speech_tagging.py
tf_core/nltoolkit/lib/similarity_matrix.py
tf_core/nltoolkit/lib/stemming.py
tf_core/nltoolkit/lib/stop_word_removal.py
tf_core/nltoolkit/lib/tagging_common.py
tf_core/nltoolkit/lib/tagging_common_parallel.py
tf_core/nltoolkit/lib/textual_data_in_out.py
tf_core/nltoolkit/lib/tokenization.py
tf_core/nltoolkit/package_data/bing_api_key.json
tf_core/nltoolkit/package_data/faroo_api_key.json
tf_core/nltoolkit/package_data/categories/017444c3-afd0-4300-9766-bedeaef10765.json
tf_core/nltoolkit/package_data/categories/2e5cfc0a-c916-45b3-b53f-c3234a408bbd.json
tf_core/nltoolkit/package_data/categories/45090e07-d869-4fb2-990a-dd108b1063cc.json
tf_core/nltoolkit/package_data/categories/46050a99-188d-40e1-90e5-0c1912059fa7.json
tf_core/nltoolkit/package_data/categories/49d5fda2-23d4-444a-a6df-3c5714d2fdfd.json
tf_core/nltoolkit/package_data/categories/4b74b12d-4767-45b1-9bb3-8872234b01fe.json
tf_core/nltoolkit/package_data/categories/53445215-f202-462e-bb3d-26814c3185b7.json
tf_core/nltoolkit/package_data/categories/57cfe571-165d-4575-90d9-28daf794e773.json
tf_core/nltoolkit/package_data/categories/5a2a3054-1e34-4e51-851e-85baaee020d4.json
tf_core-0.2.1.dist-info/DESCRIPTION.rst
tf_core-0.2.1.dist-info/METADATA
tf_core-0.2.1.dist-info/RECORD
tf_core-0.2.1.dist-info/WHEEL
tf_core-0.2.1.dist-info/metadata.json
tf_core-0.2.1.dist-info/top_level.txt
