Metadata-Version: 2.0
Name: tf-core
Version: 0.2.1
Summary: TextFlows core text mining module
Home-page: https://github.com/xflows/tf_core
Author: Matic Perovsek
Author-email: matic.perovsek@ijs.si
License: MIT License
Platform: UNKNOWN
Classifier: Development Status :: 2 - Pre-Alpha
Classifier: Environment :: Web Environment
Classifier: Framework :: Django
Classifier: Intended Audience :: Developers
Classifier: License :: OSI Approved :: MIT License
Classifier: Operating System :: OS Independent
Classifier: Programming Language :: Python
Classifier: Programming Language :: Python :: 2
Classifier: Topic :: Internet :: WWW/HTTP
Classifier: Topic :: Internet :: WWW/HTTP :: Dynamic Content
Classifier: Topic :: Scientific/Engineering :: Artificial Intelligence
Classifier: Topic :: Software Development :: Libraries
Requires-Dist: nltk (==3.2.1)
Requires-Dist: scikit-learn (==0.19.1)
Requires-Dist: python-docx
Requires-Dist: requests
Requires-Dist: pdfminer.six
Requires-Dist: pattern (==3.6)
